RagAdhocQueryDoc.py
RagPrompt.py
RagTest.py
__init__.py
ragfmk/__init__.py
ragfmk/rag.py
ragfmk/ragChromaDB.py
ragfmk/ragFAISS.py
ragfmk/elements/__init__.py
ragfmk/elements/embeddings/__init__.py
ragfmk/elements/embeddings/embedding.py
ragfmk/elements/embeddings/embeddings.py
ragfmk/elements/embeddings/ollamaEmbeddings.py
ragfmk/elements/embeddings/stEmbeddings.py
ragfmk/elements/llms/__init__.py
ragfmk/elements/llms/ollama.py
ragfmk/elements/simsearchengines/ChromaDBWrapper.py
ragfmk/elements/simsearchengines/FAISSWrapper.py
ragfmk/elements/simsearchengines/__init__.py
ragfmk/elements/wrappers/__init__.py
ragfmk/elements/wrappers/chunks.py
ragfmk/elements/wrappers/document.py
ragfmk/elements/wrappers/nearest.py
ragfmk/elements/wrappers/prompt.py
ragfmk/interfaces/IChunks.py
ragfmk/interfaces/IDocument.py
ragfmk/interfaces/IEmbeddings.py
ragfmk/interfaces/INearest.py
ragfmk/interfaces/IPrompt.py
ragfmk/interfaces/IRag.py
ragfmk/utils/CONST.py
ragfmk/utils/__init__.py
ragfmk/utils/trace.py
ragfmk-0.1.5.0.dist-info/LICENSE
ragfmk-0.1.5.0.dist-info/METADATA
ragfmk-0.1.5.0.dist-info/WHEEL
ragfmk-0.1.5.0.dist-info/entry_points.txt
ragfmk-0.1.5.0.dist-info/top_level.txt
ragfmk-0.1.5.0.dist-info/RECORD
