Metadata-Version: 2.1
Name: ragfmk
Version: 0.1.5.0
Summary: Lightweight RAG Framework: Simple and Scalable Framework with Efficient Embeddings. Leverage: FAISS, ChromaDB, and Ollama.
Author-email: Benoit Cayla <benoit@datacorner.fr>
License: MIT License
Classifier: Development Status :: 3 - Alpha
Classifier: Operating System :: OS Independent
Classifier: Environment :: Console
Classifier: Programming Language :: Python :: 3.10
Requires-Python: >=3.10
License-File: LICENSE
Requires-Dist: pandas ==2.2.1
Requires-Dist: PyMuPDF ==1.24.0
Requires-Dist: langchain ==0.1.13
Requires-Dist: sentence-transformers ==2.6.0
Requires-Dist: faiss-cpu ==1.8.0
Requires-Dist: numpyencoder ==0.3.0
Requires-Dist: langchain-experimental ==0.0.55
Requires-Dist: chromadb-client ==0.4.25.dev0
Requires-Dist: Jinja2 ==3.1.3
